MANIFEST.in
setup.py
NebulasSdkPy.egg-info/PKG-INFO
NebulasSdkPy.egg-info/SOURCES.txt
NebulasSdkPy.egg-info/dependency_links.txt
NebulasSdkPy.egg-info/requires.txt
NebulasSdkPy.egg-info/top_level.txt
nebpysdk/__init__.py
nebpysdk/example/AccountExample.py
nebpysdk/example/ApiExample.py
nebpysdk/example/TransactionExample.py
nebpysdk/example/__init__.py
nebpysdk/src/__init__.py
nebpysdk/src/account/Account.py
nebpysdk/src/account/KeyJSON.py
nebpysdk/src/account/__init__.py
nebpysdk/src/client/Admin.py
nebpysdk/src/client/Api.py
nebpysdk/src/client/HttpRequest.py
nebpysdk/src/client/Neb.py
nebpysdk/src/client/__init__.py
nebpysdk/src/core/Address.py
nebpysdk/src/core/Transaction.py
nebpysdk/src/core/TransactionBinaryPayload.py
nebpysdk/src/core/TransactionCallPayload.py
nebpysdk/src/core/TransactionDeployPayload.py
nebpysdk/src/core/TransactionPayload.py
nebpysdk/src/core/__init__.py
nebpysdk/src/crypto/__init__.py
nebpysdk/src/crypto/cipher/Cipher.py
nebpysdk/src/crypto/cipher/CryptoJSON.py
nebpysdk/src/crypto/cipher/Scrypt.py
nebpysdk/src/crypto/cipher/__init__.py
nebpysdk/src/crypto/hash/Hash.py
nebpysdk/src/crypto/hash/__init__.py
nebpysdk/src/crypto/keystore/Algorithm.py
nebpysdk/src/crypto/keystore/__init__.py
nebpysdk/src/crypto/keystore/secp256k1/ECPrivateKey.py
nebpysdk/src/crypto/keystore/secp256k1/ECPublicKey.py
nebpysdk/src/crypto/keystore/secp256k1/ECsignature.py
nebpysdk/src/crypto/keystore/secp256k1/Secp256k1.py
nebpysdk/src/crypto/keystore/secp256k1/__init__.py
nebpysdk/src/crypto/util/__init__.py
nebpysdk/src/proto/__init__.py
nebpysdk/src/proto/generated/__init__.py
nebpysdk/src/proto/generated/corepb/__init__.py
nebpysdk/src/proto/generated/corepb/addressbook_pb2.py
nebpysdk/src/proto/generated/corepb/transaction_pb2.py
nebpysdk/src/proto/generated/google/__init__.py
nebpysdk/src/proto/generated/google/protobuf/__init__.py
nebpysdk/src/proto/generated/google/protobuf/descriptor.py
nebpysdk/src/proto/generated/google/protobuf/descriptor_database.py
nebpysdk/src/proto/generated/google/protobuf/descriptor_pool.py
nebpysdk/src/proto/generated/google/protobuf/json_format.py
nebpysdk/src/proto/generated/google/protobuf/message.py
