Metadata-Version: 1.0
Name: NebulasSdkPy
Version: 0.4.0
Summary: NebulasSdkPy
Home-page: UNKNOWN
Author: GuoXiaoMin
Author-email: UNKNOWN
License: LICENSE.txt
Platform: UNKNOWN
